README
setup.py
ga4ghmongo/__init__.py
ga4ghmongo/utils.py
ga4ghmongo/version.py
ga4ghmongo.egg-info/PKG-INFO
ga4ghmongo.egg-info/SOURCES.txt
ga4ghmongo.egg-info/dependency_links.txt
ga4ghmongo.egg-info/requires.txt
ga4ghmongo.egg-info/top_level.txt
ga4ghmongo/schema/__init__.py
ga4ghmongo/schema/models/__init__.py
ga4ghmongo/schema/models/base.py
ga4ghmongo/schema/models/references.py
ga4ghmongo/schema/models/variants.py