Metadata-Version: 1.0
Name: ga4ghmongo
Version: 0.0.1.2
Summary: A document based Variant database inspired by ga4gh Variants schema
Home-page: https://github.com/Phelimb/ga4gh-mongo
Author: Phelim Bradley
Author-email: wave@phel.im
License: MIT
Platform: UNKNOWN
